Amazon_crawler/__init__.py
Amazon_crawler/client.py
Amazon_crawler/server.py
Amazon_crawler-0.0.3.dist-info/METADATA
Amazon_crawler-0.0.3.dist-info/WHEEL
Amazon_crawler-0.0.3.dist-info/top_level.txt
Amazon_crawler-0.0.3.dist-info/RECORD
