Metadata-Version: 2.1
Name: Amazon-crawler
Version: 0.0.3
Summary: A high concurrency crawler framework for Amazon
Home-page: https://github.com/NocoldBob/Amazon_crawler
Author: fastbiubiu
Author-email: fastbiubiu@163.com
License: UNKNOWN
Platform: UNKNOWN
Classifier: Programming Language :: Python :: 3
Classifier: License :: OSI Approved :: MIT License
Classifier: Operating System :: OS Independent
